monkey/__init__.py
monkey/google/__init__.py
monkey/google/api/__init__.py
monkey/google/api/auth_scopes.json
monkey/google/api/cred_providers.json
monkey/google/api/helpers.json
monkey/google/api/helpers.py
monkey/google/api/apps/__init__.py
monkey/google/api/apps/helpers.py
monkey/google/api/auth_scopes/apps_auth_scopes.json
monkey/google/api/auth_scopes/directory_auth_scopes.json
monkey/google/api/auth_scopes/drive_auth_scopes.json
monkey/google/api/auth_scopes/gmail_auth_scopes.json
monkey/google/api/directory/__init__.py
monkey/google/api/directory/helpers.py
monkey/google/api/drive/__init__.py
monkey/google/api/drive/helpers.py
monkey/google/api/gmail/__init__.py
monkey/google/api/gmail/helpers.py
monkey.google.api-0.0.1.dev11.dist-info/LICENSE.txt
monkey.google.api-0.0.1.dev11.dist-info/METADATA
monkey.google.api-0.0.1.dev11.dist-info/WHEEL
monkey.google.api-0.0.1.dev11.dist-info/top_level.txt
monkey.google.api-0.0.1.dev11.dist-info/RECORD
