Metadata-Version: 2.1
Name: monkey.google.api
Version: 0.0.1.dev11
Summary: Helper classes for Google API..
Home-page: https://bitbucket.org/monkeytechnologies/monkey-google-api/
Author: Xavier ROY
Author-email: xavier@regbuddy.eu
License: Apache License, Version 2.0
Platform: UNKNOWN
Classifier: Programming Language :: Python
Classifier: Development Status :: 1 - Planning
Classifier: Operating System :: OS Independent
Classifier: Programming Language :: Python :: 3.6
Classifier: Topic :: Software Development :: Libraries :: Python Modules
Classifier: Intended Audience :: Developers
Requires-Dist: monkey.ioc (>=0.0.1.dev3)
Requires-Dist: google-api-python-client (>=1.7.10)
Requires-Dist: google-auth (>=1.6.3)
Requires-Dist: google-auth-httplib2 (>=0.0.3)
Requires-Dist: google-auth-oauthlib (>=0.4.0)
Requires-Dist: oauth2client (>=4.1.3)
